[
    {
        "title": "上海沪剧院创作出品原创大型沪剧《敦煌女儿》",
        "date": [
            "2018-05-22T16:00:00.000Z"
        ],
        "url": "http://www.shoac.com.cn/PlayInfo.aspx?playid=16704",
        "source": "shoac"
    },
    {
        "title": "风从海上来纪念改革开放四十周年音乐会",
        "date": [
            "2018-05-23T16:00:00.000Z"
        ],
        "url": "http://www.shoac.com.cn/PlayInfo.aspx?playid=16720",
        "source": "shoac"
    },
    {
        "title": "音乐共和剧场“戏如人生”新媒体融合音乐会",
        "date": [
            "2018-05-23T16:00:00.000Z"
        ],
        "url": "http://www.shoac.com.cn/PlayInfo.aspx?playid=16732",
        "source": "shoac"
    },
    {
        "title": "陆家嘴信托荣誉呈现2018东方市民音乐会·晚场版雨中花园盛原演绎德彪西·多媒体钢琴音乐会",
        "date": [
            "2018-05-24T16:00:00.000Z"
        ],
        "url": "http://www.shoac.com.cn/PlayInfo.aspx?playid=16662",
        "source": "shoac"
    },
    {
        "title": "俄罗斯芭蕾国家剧院芭蕾舞团《天鹅湖》",
        "date": [
            "2018-05-24T16:00:00.000Z",
            "2018-05-28T16:00:00.000Z",
            "2018-05-27T16:00:00.000Z",
            "2018-06-03T16:00:00.000Z",
            "2018-06-02T16:00:00.000Z"
        ],
        "url": "http://www.shoac.com.cn/PlayInfo.aspx?playid=16689",
        "source": "shoac"
    },
    {
        "title": "俄罗斯芭蕾国家剧院芭蕾舞团《胡桃夹子》",
        "date": [
            "2018-05-25T16:00:00.000Z",
            "2018-05-30T16:00:00.000Z"
        ],
        "url": "http://www.shoac.com.cn/PlayInfo.aspx?playid=16693",
        "source": "shoac"
    },
    {
        "title": "海上雅乐·弦歌入青云闵惠芬纪念音乐会（四）",
        "date": [
            "2018-05-25T16:00:00.000Z"
        ],
        "url": "http://www.shoac.com.cn/PlayInfo.aspx?playid=16634",
        "source": "shoac"
    },
    {
        "title": "德意志童声威斯巴赫合唱团上海音乐会",
        "date": [
            "2018-05-27T16:00:00.000Z",
            "2018-05-26T16:00:00.000Z"
        ],
        "url": "http://www.shoac.com.cn/PlayInfo.aspx?playid=16688",
        "source": "shoac"
    },
    {
        "title": "“哆唻咪和大灰鸡”亲子故事音乐会《妈妈爱我》",
        "date": [
            "2018-05-25T16:00:00.000Z"
        ],
        "url": "http://www.shoac.com.cn/PlayInfo.aspx?playid=16701",
        "source": "shoac"
    },
    {
        "title": "柴可夫斯基三大经典《天鹅湖》《睡美人》《胡桃夹子》交响音乐会",
        "date": [
            "2018-05-26T16:00:00.000Z"
        ],
        "url": "http://www.shoac.com.cn/PlayInfo.aspx?playid=16700",
        "source": "shoac"
    },
    {
        "title": "旅美青年钢琴家王子翔钢琴独奏音乐会",
        "date": [
            "2018-05-26T16:00:00.000Z"
        ],
        "url": "http://www.shoac.com.cn/PlayInfo.aspx?playid=16736",
        "source": "shoac"
    },
    {
        "title": "俄罗斯芭蕾国家剧院芭蕾舞团《睡美人》",
        "date": [
            "2018-05-28T16:00:00.000Z"
        ],
        "url": "http://www.shoac.com.cn/PlayInfo.aspx?playid=16695",
        "source": "shoac"
    },
    {
        "title": "俄罗斯芭蕾国家剧院芭蕾舞团《灰姑娘》",
        "date": [
            "2018-05-29T16:00:00.000Z"
        ],
        "url": "http://www.shoac.com.cn/PlayInfo.aspx?playid=16696",
        "source": "shoac"
    },
    {
        "title": "陆家嘴信托荣誉呈现东方市民音乐会·晚场版倾听德意志斯图加特室内乐团音乐会",
        "date": [
            "2018-05-30T16:00:00.000Z"
        ],
        "url": "http://www.shoac.com.cn/PlayInfo.aspx?playid=16623",
        "source": "shoac"
    },
    {
        "title": "经典夜上海·周末爵士沙龙多啦A梦的奇妙世界·儿童节专场",
        "date": [
            "2018-05-31T16:00:00.000Z"
        ],
        "url": "http://www.shoac.com.cn/PlayInfo.aspx?playid=16673",
        "source": "shoac"
    },
    {
        "title": "俄罗斯芭蕾国家剧院芭蕾舞团亲子芭蕾舞剧《洋葱头历险记》",
        "date": [
            "2018-05-31T16:00:00.000Z"
        ],
        "url": "http://www.shoac.com.cn/PlayInfo.aspx?playid=16692",
        "source": "shoac"
    },
    {
        "title": "六·一国际儿童节特别节目燕子姐姐讲故事世界童话·古典名曲",
        "date": [
            "2018-05-31T16:00:00.000Z"
        ],
        "url": "http://www.shoac.com.cn/PlayInfo.aspx?playid=16706",
        "source": "shoac"
    },
    {
        "title": "陆家嘴信托荣誉呈现东方市民音乐会·周末版聆听大师——莫扎特交响专场上海巴罗克室内乐团音乐会",
        "date": [
            "2018-06-01T16:00:00.000Z"
        ],
        "url": "http://www.shoac.com.cn/PlayInfo.aspx?playid=16614",
        "source": "shoac"
    },
    {
        "title": "上海爱乐乐团2017-2018音乐季纪念德彪西逝世100周年音乐会",
        "date": [
            "2018-06-01T16:00:00.000Z"
        ],
        "url": "http://www.shoac.com.cn/PlayInfo.aspx?playid=16669",
        "source": "shoac"
    },
    {
        "title": "致敬圣·桑动物狂欢节六一特别音乐会",
        "date": [
            "2018-06-01T16:00:00.000Z"
        ],
        "url": "http://www.shoac.com.cn/PlayInfo.aspx?playid=16730",
        "source": "shoac"
    },
    {
        "title": "巴赫《约翰生命之歌》大型合唱套曲作品音乐会上海国际联盟合唱团&附属管弦乐团",
        "date": [
            "2018-06-02T16:00:00.000Z"
        ],
        "url": "http://www.shoac.com.cn/PlayInfo.aspx?playid=16724",
        "source": "shoac"
    },
    {
        "title": "未来大师系列致敬大师：舒伯特与拉赫玛尼诺夫伊利亚·伊亭钢琴独奏音乐会",
        "date": [
            "2018-06-02T16:00:00.000Z"
        ],
        "url": "http://www.shoac.com.cn/PlayInfo.aspx?playid=16648",
        "source": "shoac"
    },
    {
        "title": "新古典钢琴家鲁多维科·艾奥迪2018巡演·上海站",
        "date": [
            "2018-06-06T16:00:00.000Z",
            "2018-06-05T16:00:00.000Z"
        ],
        "url": "http://www.shoac.com.cn/PlayInfo.aspx?playid=16715",
        "source": "shoac"
    },
    {
        "title": "管风琴演奏家 HEE-SUNG KIM2018亚洲巡演音乐会",
        "date": [
            "2018-06-06T16:00:00.000Z"
        ],
        "url": "http://www.shoac.com.cn/PlayInfo.aspx?playid=16731",
        "source": "shoac"
    },
    {
        "title": "未来大师系列致敬大师：德彪西与拉威尔法国菲勒亚斯弦乐四重奏音乐会",
        "date": [
            "2018-06-07T16:00:00.000Z"
        ],
        "url": "http://www.shoac.com.cn/PlayInfo.aspx?playid=16649",
        "source": "shoac"
    },
    {
        "title": "西班牙钢琴王子Mario Alonso独奏音乐会",
        "date": [
            "2018-06-07T16:00:00.000Z"
        ],
        "url": "http://www.shoac.com.cn/PlayInfo.aspx?playid=16660",
        "source": "shoac"
    },
    {
        "title": "“传说中的牧神之笛”宝岛台湾著名长笛演奏家梅启生上海音乐会",
        "date": [
            "2018-06-08T16:00:00.000Z"
        ],
        "url": "http://www.shoac.com.cn/PlayInfo.aspx?playid=16670",
        "source": "shoac"
    },
    {
        "title": "美国亚利桑那图森男童合唱团音乐会",
        "date": [
            "2018-06-09T16:00:00.000Z"
        ],
        "url": "http://www.shoac.com.cn/PlayInfo.aspx?playid=16727",
        "source": "shoac"
    },
    {
        "title": "陆家嘴信托荣誉呈现东方市民音乐会·周末版斯拉夫情结上海爱乐乐团交响音乐会",
        "date": [
            "2018-06-15T16:00:00.000Z"
        ],
        "url": "http://www.shoac.com.cn/PlayInfo.aspx?playid=16615",
        "source": "shoac"
    },
    {
        "title": "古典明星演绎浪漫法兰西小提琴王子五岛龙上海音乐会",
        "date": [
            "2018-06-15T16:00:00.000Z"
        ],
        "url": "http://www.shoac.com.cn/PlayInfo.aspx?playid=16661",
        "source": "shoac"
    },
    {
        "title": "东艺·央华戏剧季话剧《戴茜今晚嫁给谁》",
        "date": [
            "2018-06-18T16:00:00.000Z",
            "2018-06-17T16:00:00.000Z"
        ],
        "url": "http://www.shoac.com.cn/PlayInfo.aspx?playid=16683",
        "source": "shoac"
    },
    {
        "title": "“天空之城”久石让&宫崎骏经典动漫作品视听音乐会",
        "date": [
            "2018-06-16T16:00:00.000Z"
        ],
        "url": "http://www.shoac.com.cn/PlayInfo.aspx?playid=16699",
        "source": "shoac"
    },
    {
        "title": "纪念伯格曼诞辰百年法国明星版话剧《婚姻生活》",
        "date": [
            "2018-06-21T16:00:00.000Z",
            "2018-06-20T16:00:00.000Z"
        ],
        "url": "http://www.shoac.com.cn/PlayInfo.aspx?playid=16677",
        "source": "shoac"
    },
    {
        "title": "2018谢春花“点心”全国巡回演唱会上海站",
        "date": [
            "2018-06-19T16:00:00.000Z"
        ],
        "url": "http://www.shoac.com.cn/PlayInfo.aspx?playid=16733",
        "source": "shoac"
    },
    {
        "title": "未来大师系列夏日时光“亚洲指弹天王” 陈彦宏指弹吉他音乐会",
        "date": [
            "2018-06-22T16:00:00.000Z"
        ],
        "url": "http://www.shoac.com.cn/PlayInfo.aspx?playid=16650",
        "source": "shoac"
    },
    {
        "title": "猫和老鼠的贝多芬古典音乐启蒙亲子钢琴快乐视听音乐会",
        "date": [
            "2018-06-22T16:00:00.000Z"
        ],
        "url": "http://www.shoac.com.cn/PlayInfo.aspx?playid=16702",
        "source": "shoac"
    },
    {
        "title": "一生必听的电影音乐《卡农》《海上钢琴师》《教父》《汉尼拔》钢琴小提琴大提琴浪漫邂逅音乐会",
        "date": [
            "2018-06-22T16:00:00.000Z"
        ],
        "url": "http://www.shoac.com.cn/PlayInfo.aspx?playid=16703",
        "source": "shoac"
    },
    {
        "title": "2018豆荚宝宝儿童音乐会击乐精灵开Party",
        "date": [
            "2018-06-24T16:00:00.000Z",
            "2018-06-23T16:00:00.000Z",
            "2018-06-24T16:00:00.000Z",
            "2018-06-23T16:00:00.000Z"
        ],
        "url": "http://www.shoac.com.cn/PlayInfo.aspx?playid=16698",
        "source": "shoac"
    },
    {
        "title": "陆家嘴信托荣誉呈现2018东方市民音乐会·晚场版今夜无人入睡经典歌剧选段&中外名歌名曲音乐会",
        "date": [
            "2018-06-23T16:00:00.000Z"
        ],
        "url": "http://www.shoac.com.cn/PlayInfo.aspx?playid=16712",
        "source": "shoac"
    },
    {
        "title": "红色中国心俄美女博士小提琴家玛丽安娜中国作品音乐会",
        "date": [
            "2018-06-23T16:00:00.000Z"
        ],
        "url": "http://www.shoac.com.cn/PlayInfo.aspx?playid=16671",
        "source": "shoac"
    },
    {
        "title": "在那遥远的地方王洛宾作品大型交响音乐会",
        "date": [
            "2018-06-25T16:00:00.000Z"
        ],
        "url": "http://www.shoac.com.cn/PlayInfo.aspx?playid=16716",
        "source": "shoac"
    },
    {
        "title": "《新时代·新征程》千手观音走进上海大型特殊文艺晚会",
        "date": [
            "2018-06-26T16:00:00.000Z"
        ],
        "url": "http://www.shoac.com.cn/PlayInfo.aspx?playid=16711",
        "source": "shoac"
    },
    {
        "title": "魔法钢琴&肖邦短篇奇幻视听音乐会",
        "date": [
            "2018-06-27T16:00:00.000Z",
            "2018-10-01T16:00:00.000Z"
        ],
        "url": "http://www.shoac.com.cn/PlayInfo.aspx?playid=16709",
        "source": "shoac"
    },
    {
        "title": "陆家嘴信托荣誉呈现2018东方市民音乐会·晚场版音·为爱——维也纳爱乐-柏林爱乐 明星首席音乐会",
        "date": [
            "2018-06-28T16:00:00.000Z"
        ],
        "url": "http://www.shoac.com.cn/PlayInfo.aspx?playid=16681",
        "source": "shoac"
    },
    {
        "title": "东艺·央华戏剧季法国阿维尼翁戏剧节优秀剧目《西贡》",
        "date": [
            "2018-06-30T16:00:00.000Z",
            "2018-06-29T16:00:00.000Z"
        ],
        "url": "http://www.shoac.com.cn/PlayInfo.aspx?playid=16684",
        "source": "shoac"
    },
    {
        "title": "海上雅乐·关山月琴筝雅歌音乐会",
        "date": [
            "2018-06-29T16:00:00.000Z"
        ],
        "url": "http://www.shoac.com.cn/PlayInfo.aspx?playid=16635",
        "source": "shoac"
    },
    {
        "title": "2018《歌唱祖国》经典名曲交响音乐会",
        "date": [
            "2018-06-29T16:00:00.000Z"
        ],
        "url": "http://www.shoac.com.cn/PlayInfo.aspx?playid=16723",
        "source": "shoac"
    },
    {
        "title": "网站技术测试-请勿购买请勿购买",
        "date": [
            "2018-06-30T16:00:00.000Z"
        ],
        "url": "http://www.shoac.com.cn/PlayInfo.aspx?playid=16427",
        "source": "shoac"
    },
    {
        "title": "海上雅乐·齐风鲁韵高培芬诸城派古琴音乐会",
        "date": [
            "2018-09-14T16:00:00.000Z"
        ],
        "url": "http://www.shoac.com.cn/PlayInfo.aspx?playid=16734",
        "source": "shoac"
    },
    {
        "title": "2018未来大师 独奏重奏系列音乐会致敬大师：德彪西与舒伯特中国 – 王葛美伦钢琴独奏音乐会",
        "date": [
            "2018-09-19T16:00:00.000Z"
        ],
        "url": "http://www.shoac.com.cn/PlayInfo.aspx?playid=16651",
        "source": "shoac"
    },
    {
        "title": "经典夜上海·周末爵士沙龙老情人·老歌专场",
        "date": [
            "2018-09-20T16:00:00.000Z"
        ],
        "url": "http://www.shoac.com.cn/PlayInfo.aspx?playid=16674",
        "source": "shoac"
    },
    {
        "title": "东艺·央华戏剧季舞台剧《明年此时》",
        "date": [
            "2018-09-22T16:00:00.000Z",
            "2018-09-21T16:00:00.000Z"
        ],
        "url": "http://www.shoac.com.cn/PlayInfo.aspx?playid=16717",
        "source": "shoac"
    },
    {
        "title": "陆家嘴信托荣誉呈现东方市民音乐会·晚场版金色大厅的音乐瞬间 - 维也纳音乐平台室内乐团音乐会",
        "date": [
            "2018-09-21T16:00:00.000Z"
        ],
        "url": "http://www.shoac.com.cn/PlayInfo.aspx?playid=16682",
        "source": "shoac"
    },
    {
        "title": "2018未来大师 独奏重奏系列音乐会情迷法兰西法国 - 巴黎顽童香颂四重奏音乐会",
        "date": [
            "2018-09-28T16:00:00.000Z",
            "2018-09-27T16:00:00.000Z"
        ],
        "url": "http://www.shoac.com.cn/PlayInfo.aspx?playid=16652",
        "source": "shoac"
    },
    {
        "title": "西班牙钢琴家马诺洛·卡拉斯科钢琴独奏音乐会",
        "date": [
            "2018-09-27T16:00:00.000Z"
        ],
        "url": "http://www.shoac.com.cn/PlayInfo.aspx?playid=16725",
        "source": "shoac"
    },
    {
        "title": "2018未来大师 独奏重奏系列音乐会梦醒时分法国 – 阿提斯钢琴三重奏音乐会",
        "date": [
            "2018-10-01T16:00:00.000Z"
        ],
        "url": "http://www.shoac.com.cn/PlayInfo.aspx?playid=16653",
        "source": "shoac"
    },
    {
        "title": "东艺·央华戏剧季舞台剧《新原野》",
        "date": [
            "2018-10-06T16:00:00.000Z",
            "2018-10-05T16:00:00.000Z"
        ],
        "url": "http://www.shoac.com.cn/PlayInfo.aspx?playid=16718",
        "source": "shoac"
    },
    {
        "title": "第二十届中国上海国际艺术节参演剧目云门２《十三声》",
        "date": [
            "2018-10-21T16:00:00.000Z",
            "2018-10-20T16:00:00.000Z"
        ],
        "url": "http://www.shoac.com.cn/PlayInfo.aspx?playid=16697",
        "source": "shoac"
    },
    {
        "title": "海上雅乐·梅花三弄陆笑姿王俊侃琴箫音乐会",
        "date": [
            "2018-10-19T16:00:00.000Z"
        ],
        "url": "http://www.shoac.com.cn/PlayInfo.aspx?playid=16735",
        "source": "shoac"
    },
    {
        "title": "2018未来大师 独奏重奏系列音乐会火舞西班牙西班牙 –帕布罗·维勒盖斯吉他独奏音乐会",
        "date": [
            "2018-10-20T16:00:00.000Z"
        ],
        "url": "http://www.shoac.com.cn/PlayInfo.aspx?playid=16654",
        "source": "shoac"
    },
    {
        "title": "经典夜上海·周末爵士沙龙魅影·万圣节专场",
        "date": [
            "2018-10-25T16:00:00.000Z"
        ],
        "url": "http://www.shoac.com.cn/PlayInfo.aspx?playid=16678",
        "source": "shoac"
    },
    {
        "title": "2018未来大师 独奏重奏系列音乐会北欧童话瑞典– 卡尔·彼得森钢琴独奏音乐会",
        "date": [
            "2018-10-27T16:00:00.000Z"
        ],
        "url": "http://www.shoac.com.cn/PlayInfo.aspx?playid=16655",
        "source": "shoac"
    },
    {
        "title": "2018未来大师 独奏重奏系列音乐会致敬大师：贝多芬与拉赫玛尼诺夫俄罗斯 – 鲍里斯·吉尔特伯格钢琴独奏音乐会",
        "date": [
            "2018-11-06T16:00:00.000Z"
        ],
        "url": "http://www.shoac.com.cn/PlayInfo.aspx?playid=16656",
        "source": "shoac"
    },
    {
        "title": "经典夜上海·周末爵士沙龙疯狂的爵士·经典爵士乐专场",
        "date": [
            "2018-11-22T16:00:00.000Z"
        ],
        "url": "http://www.shoac.com.cn/PlayInfo.aspx?playid=16679",
        "source": "shoac"
    },
    {
        "title": "2018未来大师 独奏重奏系列音乐会逐舞之乐中国 – 王弢单簧管独奏音乐会",
        "date": [
            "2018-11-24T16:00:00.000Z"
        ],
        "url": "http://www.shoac.com.cn/PlayInfo.aspx?playid=16657",
        "source": "shoac"
    },
    {
        "title": "2018未来大师 独奏重奏系列音乐会拉美印象法国 - 文森·佩拉尼与弗朗索瓦·萨尔科手风琴/大提琴音乐会",
        "date": [
            "2018-12-13T16:00:00.000Z"
        ],
        "url": "http://www.shoac.com.cn/PlayInfo.aspx?playid=16658",
        "source": "shoac"
    },
    {
        "title": "2018未来大师 独奏重奏系列音乐会竖琴的冥想奥地利 - 玛蒂娜·斯托克独奏音乐会",
        "date": [
            "2018-12-20T16:00:00.000Z"
        ],
        "url": "http://www.shoac.com.cn/PlayInfo.aspx?playid=16659",
        "source": "shoac"
    },
    {
        "title": "大型多媒体视觉芭蕾舞剧《天鹅湖》俄罗斯皇家芭蕾舞团",
        "date": [
            "2018-12-23T16:00:00.000Z",
            "2018-12-22T16:00:00.000Z"
        ],
        "url": "http://www.shoac.com.cn/PlayInfo.aspx?playid=16722",
        "source": "shoac"
    },
    {
        "title": "经典夜上海·周末爵士沙龙月下的圣诞老人·圣诞节专场",
        "date": [
            "2018-12-23T16:00:00.000Z"
        ],
        "url": "http://www.shoac.com.cn/PlayInfo.aspx?playid=16680",
        "source": "shoac"
    },
    {
        "title": "西本智实与日本辉煌艺术交响乐团上海新年音乐会",
        "date": [
            "2018-12-24T16:00:00.000Z"
        ],
        "url": "http://www.shoac.com.cn/PlayInfo.aspx?playid=16729",
        "source": "shoac"
    },
    {
        "title": "维也纳春之声交响乐团新年音乐会",
        "date": [
            "2018-12-28T16:00:00.000Z",
            "2018-12-27T16:00:00.000Z",
            "2019-12-28T16:00:00.000Z",
            "2019-12-27T16:00:00.000Z"
        ],
        "url": "http://www.shoac.com.cn/PlayInfo.aspx?playid=16713",
        "source": "shoac"
    },
    {
        "title": "巴赫《哥德堡变奏曲》安宁、焦元溥对谈音乐会",
        "date": [
            "2019-01-18T16:00:00.000Z"
        ],
        "url": "http://www.shoac.com.cn/PlayInfo.aspx?playid=16728",
        "source": "shoac"
    }
]